{
  "base": "https://aiphantomtraders.com",
  "startedAt": "2026-06-23T17:07:36.276Z",
  "pages": [
    {
      "id": "home",
      "viewport": "desktop",
      "url": "https://aiphantomtraders.com/",
      "ok": true,
      "httpStatus": 200,
      "consoleErrors": []
    },
    {
      "id": "home",
      "viewport": "mobile",
      "url": "https://aiphantomtraders.com/",
      "ok": true,
      "httpStatus": 200,
      "consoleErrors": []
    },
    {
      "id": "features",
      "viewport": "desktop",
      "url": "https://aiphantomtraders.com/#page-features",
      "ok": true,
      "httpStatus": 200,
      "consoleErrors": []
    },
    {
      "id": "features",
      "viewport": "mobile",
      "url": "https://aiphantomtraders.com/#page-features",
      "ok": true,
      "httpStatus": 200,
      "consoleErrors": []
    },
    {
      "id": "pricing",
      "viewport": "desktop",
      "url": "https://aiphantomtraders.com/#page-pricing",
      "ok": true,
      "httpStatus": 200,
      "consoleErrors": []
    },
    {
      "id": "pricing",
      "viewport": "mobile",
      "url": "https://aiphantomtraders.com/#page-pricing",
      "ok": true,
      "httpStatus": 200,
      "consoleErrors": []
    },
    {
      "id": "products",
      "viewport": "desktop",
      "url": "https://aiphantomtraders.com/#page-products",
      "ok": true,
      "httpStatus": 200,
      "consoleErrors": []
    },
    {
      "id": "products",
      "viewport": "mobile",
      "url": "https://aiphantomtraders.com/#page-products",
      "ok": true,
      "httpStatus": 200,
      "consoleErrors": []
    },
    {
      "id": "blog",
      "viewport": "desktop",
      "url": "https://aiphantomtraders.com/#page-blog",
      "ok": true,
      "httpStatus": 200,
      "consoleErrors": []
    },
    {
      "id": "blog",
      "viewport": "mobile",
      "url": "https://aiphantomtraders.com/#page-blog",
      "ok": true,
      "httpStatus": 200,
      "consoleErrors": []
    },
    {
      "id": "discord",
      "viewport": "desktop",
      "url": "https://aiphantomtraders.com/#page-discord",
      "ok": true,
      "httpStatus": 200,
      "consoleErrors": []
    },
    {
      "id": "discord",
      "viewport": "mobile",
      "url": "https://aiphantomtraders.com/#page-discord",
      "ok": true,
      "httpStatus": 200,
      "consoleErrors": []
    },
    {
      "id": "dashboard",
      "viewport": "desktop",
      "url": "https://aiphantomtraders.com/#page-dashboard",
      "ok": true,
      "httpStatus": 200,
      "consoleErrors": []
    },
    {
      "id": "dashboard",
      "viewport": "mobile",
      "url": "https://aiphantomtraders.com/#page-dashboard",
      "ok": true,
      "httpStatus": 200,
      "consoleErrors": []
    },
    {
      "id": "signup",
      "viewport": "desktop",
      "url": "https://aiphantomtraders.com/#page-signup",
      "ok": true,
      "httpStatus": 200,
      "consoleErrors": []
    },
    {
      "id": "signup",
      "viewport": "mobile",
      "url": "https://aiphantomtraders.com/#page-signup",
      "ok": true,
      "httpStatus": 200,
      "consoleErrors": []
    },
    {
      "id": "legal",
      "viewport": "desktop",
      "url": "https://aiphantomtraders.com/#page-legal",
      "ok": true,
      "httpStatus": 200,
      "consoleErrors": []
    },
    {
      "id": "legal",
      "viewport": "mobile",
      "url": "https://aiphantomtraders.com/#page-legal",
      "ok": true,
      "httpStatus": 200,
      "consoleErrors": []
    },
    {
      "id": "docs",
      "viewport": "desktop",
      "url": "https://aiphantomtraders.com/#page-docs",
      "ok": true,
      "httpStatus": 200,
      "consoleErrors": []
    },
    {
      "id": "docs",
      "viewport": "mobile",
      "url": "https://aiphantomtraders.com/#page-docs",
      "ok": true,
      "httpStatus": 200,
      "consoleErrors": []
    },
    {
      "id": "store",
      "viewport": "desktop",
      "url": "https://aiphantomtraders.com/#page-store",
      "ok": true,
      "httpStatus": 200,
      "consoleErrors": []
    },
    {
      "id": "store",
      "viewport": "mobile",
      "url": "https://aiphantomtraders.com/#page-store",
      "ok": true,
      "httpStatus": 200,
      "consoleErrors": []
    }
  ],
  "leaks": [],
  "ticker": {
    "grid": {
      "SPY": "−1.04%",
      "QQQ": "−2.76%",
      "IWM": "−0.44%",
      "NVDA": "−3.23%",
      "TSLA": "−5.15%",
      "AAPL": "+0.45%",
      "MSFT": "+1.49%",
      "AMZN": "+0.71%",
      "META": "+0.12%",
      "GOOGL": "−0.67%",
      "AMD": "−5.65%",
      "NFLX": "+0.43%",
      "COIN": "−4.05%",
      "PLTR": "−0.44%",
      "MSTR": "−3.97%",
      "SMCI": "−4.60%",
      "CRWD": "+1.81%",
      "ORCL": "−3.18%",
      "UBER": "−0.03%",
      "PYPL": "−0.99%",
      "MARA": "−0.94%",
      "RIOT": "−0.03%",
      "HOOD": "−1.30%",
      "SOFI": "+2.40%",
      "BAC": "+0.66%",
      "INTC": "−5.02%",
      "DIS": "+1.03%",
      "SNAP": "−3.46%",
      "LYFT": "+0.07%",
      "TGT": "+3.54%",
      "NKE": "−0.63%",
      "COF": "−1.13%"
    },
    "tape": {
      "SPY": "736.63",
      "QQQ": "717.58",
      "IWM": "296.88",
      "NVDA": "201.92",
      "TSLA": "384.18",
      "AAPL": "298.34",
      "MSFT": "372.80",
      "AMZN": "234.45",
      "META": "564.53",
      "GOOGL": "347.32",
      "AMD": "520.48",
      "NFLX": "73.19",
      "COIN": "158.16",
      "PLTR": "118.97",
      "MSTR": "105.11",
      "SMCI": "33.83",
      "CRWD": "687.68",
      "ORCL": "172.14",
      "UBER": "77.47",
      "PYPL": "41.92",
      "MARA": "14.71",
      "RIOT": "28.62",
      "HOOD": "104.34",
      "SOFI": "17.51",
      "BAC": "57.75",
      "INTC": "133.87",
      "DIS": "103.51",
      "SNAP": "4.47",
      "LYFT": "14.23",
      "TGT": "134.32",
      "NKE": "42.92",
      "COF": "198.44"
    },
    "clock": "MARKET · 17:07:46 ET"
  },
  "marketApi": {
    "status": 200,
    "body": "[]"
  },
  "featureErrors": [],
  "findings": [],
  "finishedAt": "2026-06-23T17:09:52.805Z"
}